{"Total":232495,"Page":11625,"Letters":[{"SuperVision":{"UnderSupervision":0,"AdditionalInfo":"","Reasons":[]},"TracingNo":586840,"Symbol":"سخاش","CompanyName":"سیمان خاش","UnderSupervision":0,"Title":"گزارش فعالیت ماهانه دوره ۱ ماهه منتهی به ۱۳۹۸/۰۸/۳۰","LetterCode":"ن-۳۰","SentDateTime":"۱۳۹۸/۰۹/۰۳ ۱۴:۵۱:۰۰","PublishDateTime":"۱۳۹۸/۰۹/۰۳ ۱۴:۵۱:۰۰","HasHtml":true,"Url":"/Reports/Decision.aspx?LetterSerial=nKa5x9nS7e6MNbSKqbfapA%3D%3D&rt=0&let=58&ct=0&ft=-1","HasExcel":true,"HasPdf":true,"HasXbrl":false,"HasAttachment":false,"AttachmentUrl":"","PdfUrl":"DownloadFile.aspx?hs=nKa5x9nS7e6MNbSKqbfapA%3d%3d&ft=1005&let=58","ExcelUrl":"https://excel.codal.ir/service/Excel/GetAll/nKa5x9nS7e6MNbSKqbfapA%3d%3d/0","XbrlUrl":"","TedanUrl":"http://www.tedan.ir"},{"SuperVision":{"UnderSupervision":0,"AdditionalInfo":"","Reasons":[]},"TracingNo":586095,"Symbol":"فجر","CompanyName":"فولاد امیرکبیر کاشان","UnderSupervision":0,"Title":"گزارش فعالیت ماهانه دوره ۱ ماهه منتهی به ۱۳۹۸/۰۸/۳۰","LetterCode":"ن-۳۰","SentDateTime":"۱۳۹۸/۰۹/۰۳ ۱۴:۴۸:۳۲","PublishDateTime":"۱۳۹۸/۰۹/۰۳ ۱۴:۴۸:۳۲","HasHtml":true,"Url":"/Reports/Decision.aspx?LetterSerial=SFr5%2B4pZhzKFySQhFROKHA%3D%3D&rt=0&let=58&ct=0&ft=-1","HasExcel":true,"HasPdf":true,"HasXbrl":false,"HasAttachment":false,"AttachmentUrl":"","PdfUrl":"DownloadFile.aspx?hs=SFr5%2b4pZhzKFySQhFROKHA%3d%3d&ft=1005&let=58","ExcelUrl":"https://excel.codal.ir/service/Excel/GetAll/SFr5%2b4pZhzKFySQhFROKHA%3d%3d/0","XbrlUrl":"","TedanUrl":"http://www.tedan.ir"},{"SuperVision":{"UnderSupervision":3,"AdditionalInfo":"","Reasons":["نیاز به بررسی وضعیت شفافیت اطلاعاتی ناشر"]},"TracingNo":586899,"Symbol":"وآداک","CompanyName":"صنعت و تجارت آداک","UnderSupervision":0,"Title":"تعلیق نماد معاملاتی ناشر به استناد بند ۷ ماده ۱۳مکرر۲ دستورالعمل اجرایی نحوه انجام معاملات اوراق بهادار در فرابورس ایران","LetterCode":"ف ب-۱۳","SentDateTime":"۱۳۹۸/۰۹/۰۳ ۱۴:۴۷:۲۰","PublishDateTime":"۱۳۹۸/۰۹/۰۳ ۱۴:۴۷:۲۰","HasHtml":true,"Url":"/Reports/Decision.aspx?LetterSerial=RcDXKZbnROKkuBaaHKKZFA%3D%3D&rt=2&let=169&ct=0&ft=-1","HasExcel":false,"HasPdf":true,"HasXbrl":false,"HasAttachment":false,"AttachmentUrl":"","PdfUrl":"DownloadFile.aspx?hs=RcDXKZbnROKkuBaaHKKZFA%3d%3d&ft=1005&let=169","ExcelUrl":"","XbrlUrl":"","TedanUrl":"http://www.tedan.ir"},{"SuperVision":{"UnderSupervision":3,"AdditionalInfo":"","Reasons":["نیاز به بررسی وضعیت شفافیت اطلاعاتی ناشر"]},"TracingNo":586722,"Symbol":"آینده","CompanyName":"بازرگانی صنعتی آینده سازان بهشت پارس","UnderSupervision":0,"Title":"اطلاعات و صورت‌های مالی میاندوره‌ای  دوره ۶ ماهه منتهی به ۱۳۹۸/۰۶/۳۱ (حسابرسی شده) (شرکت توسعه میادین میوه و تره بار بهشت پارس)","LetterCode":"ن-۱۰","SentDateTime":"۱۳۹۸/۰۹/۰۳ ۱۴:۴۶:۰۷","PublishDateTime":"۱۳۹۸/۰۹/۰۳ ۱۴:۴۶:۰۷","HasHtml":true,"Url":"/Reports/Decision.aspx?LetterSerial=okUhuMd4sm%2BOV6WB5nxsvw%3D%3D&rt=5&let=6&ct=0&ft=-1","HasExcel":true,"HasPdf":true,"HasXbrl":false,"HasAttachment":true,"AttachmentUrl":"/Reports/Attachment.aspx?LetterSerial=okUhuMd4sm%2bOV6WB5nxsvw%3d%3d","PdfUrl":"DownloadFile.aspx?hs=okUhuMd4sm%2bOV6WB5nxsvw%3d%3d&ft=1005&let=6","ExcelUrl":"https://excel.codal.ir/service/Excel/GetAll/okUhuMd4sm%2bOV6WB5nxsvw%3d%3d/0","XbrlUrl":"","TedanUrl":"http://www.tedan.ir"},{"SuperVision":{"UnderSupervision":0,"AdditionalInfo":"","Reasons":[]},"TracingNo":586895,"Symbol":"ره آورد ثابت","CompanyName":"صندوق سرمایه گذاری ره آورد آباد مسکن ","UnderSupervision":0,"Title":"صورت وضعیت پورتفوی صندوق سرمایه گذاری دوره ۱ ماهه منتهی به ۱۳۹۸/۰۸/۳۰","LetterCode":"","SentDateTime":"۱۳۹۸/۰۹/۰۳ ۱۴:۴۶:۰۶","PublishDateTime":"۱۳۹۸/۰۹/۰۳ ۱۴:۴۶:۰۶","HasHtml":false,"Url":"/Reports/Attachment.aspx?LetterSerial=uSUQQQaQQQcqzEV0QQQaQQQQe0l%2btGkH5A%3d%3d","HasExcel":false,"HasPdf":false,"HasXbrl":false,"HasAttachment":true,"AttachmentUrl":"/Reports/Attachment.aspx?LetterSerial=uSUQQQaQQQcqzEV0QQQaQQQQe0l%2btGkH5A%3d%3d","PdfUrl":"","ExcelUrl":"","XbrlUrl":"","TedanUrl":"http://www.tedan.ir"},{"SuperVision":{"UnderSupervision":0,"AdditionalInfo":"","Reasons":[]},"TracingNo":586871,"Symbol":"امید بازار","CompanyName":"صندوق سرمایه گذاری بازارگردان امید ایرانیان(بازارگردانی)","UnderSupervision":0,"Title":"تصمیمات مجمع صندوق سرمایه گذاری","LetterCode":"","SentDateTime":"۱۳۹۸/۰۹/۰۳ ۱۴:۴۴:۴۹","PublishDateTime":"۱۳۹۸/۰۹/۰۳ ۱۴:۴۴:۴۹","HasHtml":true,"Url":"/Reports/Decision.aspx?LetterSerial=VNjyY5eKggK8EAQS1TrqZQ%3D%3D&rt=2&let=122&ct=5&ft=7","HasExcel":false,"HasPdf":true,"HasXbrl":false,"HasAttachment":true,"AttachmentUrl":"/Reports/Attachment.aspx?LetterSerial=VNjyY5eKggK8EAQS1TrqZQ%3d%3d","PdfUrl":"DownloadFile.aspx?hs=VNjyY5eKggK8EAQS1TrqZQ%3d%3d&ft=1005&let=122","ExcelUrl":"","XbrlUrl":"","TedanUrl":"http://www.tedan.ir"},{"SuperVision":{"UnderSupervision":0,"AdditionalInfo":"","Reasons":[]},"TracingNo":586876,"Symbol":"زقیام ","CompanyName":"کشت و دام قیام اصفهان ","UnderSupervision":0,"Title":"پیشنهاد هیئت مدیره به مجمع عمومی فوق العاده در خصوص افزایش سرمایه","LetterCode":"ن-۶۰","SentDateTime":"۱۳۹۸/۰۹/۰۳ ۱۴:۴۳:۱۱","PublishDateTime":"۱۳۹۸/۰۹/۰۳ ۱۴:۴۳:۱۱","HasHtml":true,"Url":"/Reports/Decision.aspx?LetterSerial=L9wmwKox0wstfCuoiH5TSQ%3D%3D&rt=0&let=55&ct=0&ft=-1","HasExcel":false,"HasPdf":true,"HasXbrl":false,"HasAttachment":true,"AttachmentUrl":"/Reports/Attachment.aspx?LetterSerial=L9wmwKox0wstfCuoiH5TSQ%3d%3d","PdfUrl":"DownloadFile.aspx?hs=L9wmwKox0wstfCuoiH5TSQ%3d%3d&ft=1005&let=55","ExcelUrl":"","XbrlUrl":"","TedanUrl":"http://www.tedan.ir"},{"SuperVision":{"UnderSupervision":0,"AdditionalInfo":"","Reasons":[]},"TracingNo":586163,"Symbol":"خبهمن","CompanyName":"گروه بهمن","UnderSupervision":0,"Title":"گزارش فعالیت ماهانه دوره ۱ ماهه منتهی به ۱۳۹۸/۰۸/۳۰","LetterCode":"ن-۳۱","SentDateTime":"۱۳۹۸/۰۹/۰۳ ۱۴:۳۶:۲۸","PublishDateTime":"۱۳۹۸/۰۹/۰۳ ۱۴:۳۶:۲۸","HasHtml":true,"Url":"/Reports/Decision.aspx?LetterSerial=MmL2v3WCcnmLqQQQaQQQVYyeFc4A%3D%3D&rt=2&let=8&ct=0&ft=-1","HasExcel":true,"HasPdf":true,"HasXbrl":false,"HasAttachment":false,"AttachmentUrl":"","PdfUrl":"DownloadFile.aspx?hs=MmL2v3WCcnmLqQQQaQQQVYyeFc4A%3d%3d&ft=1005&let=8","ExcelUrl":"https://excel.codal.ir/service/Excel/GetAll/MmL2v3WCcnmLqQQQaQQQVYyeFc4A%3d%3d/0","XbrlUrl":"","TedanUrl":"http://www.tedan.ir"},{"SuperVision":{"UnderSupervision":0,"AdditionalInfo":"","Reasons":[]},"TracingNo":586853,"Symbol":"قشهد","CompanyName":"شهد(قند خوی)","UnderSupervision":0,"Title":"گزارش فعالیت ماهانه دوره ۱ ماهه منتهی به ۱۳۹۸/۰۸/۳۰","LetterCode":"ن-۳۰","SentDateTime":"۱۳۹۸/۰۹/۰۳ ۱۴:۳۶:۱۰","PublishDateTime":"۱۳۹۸/۰۹/۰۳ ۱۴:۳۶:۱۰","HasHtml":true,"Url":"/Reports/Decision.aspx?LetterSerial=Lz3wjVvAZk6DmO5vuhWzZg%3D%3D&rt=0&let=58&ct=0&ft=-1","HasExcel":true,"HasPdf":true,"HasXbrl":false,"HasAttachment":false,"AttachmentUrl":"","PdfUrl":"DownloadFile.aspx?hs=Lz3wjVvAZk6DmO5vuhWzZg%3d%3d&ft=1005&let=58","ExcelUrl":"https://excel.codal.ir/service/Excel/GetAll/Lz3wjVvAZk6DmO5vuhWzZg%3d%3d/0","XbrlUrl":"","TedanUrl":"http://www.tedan.ir"},{"SuperVision":{"UnderSupervision":0,"AdditionalInfo":"","Reasons":[]},"TracingNo":586862,"Symbol":"سدشت","CompanyName":"صنایع سیمان دشتستان","UnderSupervision":0,"Title":"گزارش کنترل های داخلی دوره ۱۲ ماهه منتهی به ۱۳۹۸/۰۶/۳۱","LetterCode":"ن-۱۲","SentDateTime":"۱۳۹۸/۰۹/۰۳ ۱۴:۳۱:۴۹","PublishDateTime":"۱۳۹۸/۰۹/۰۳ ۱۴:۳۱:۴۹","HasHtml":true,"Url":"/Reports/Decision.aspx?LetterSerial=sE43ivp70hHCEwAIRVSuSA%3D%3D&rt=0&let=90&ct=0&ft=-1","HasExcel":false,"HasPdf":true,"HasXbrl":false,"HasAttachment":true,"AttachmentUrl":"/Reports/Attachment.aspx?LetterSerial=sE43ivp70hHCEwAIRVSuSA%3d%3d","PdfUrl":"DownloadFile.aspx?hs=sE43ivp70hHCEwAIRVSuSA%3d%3d&ft=1005&let=90","ExcelUrl":"","XbrlUrl":"","TedanUrl":"http://www.tedan.ir"},{"SuperVision":{"UnderSupervision":0,"AdditionalInfo":"","Reasons":[]},"TracingNo":586886,"Symbol":"فنورد","CompanyName":"نورد و تولید قطعات فولادی","UnderSupervision":0,"Title":"شفاف سازی در خصوص نوسان قیمت سهام","LetterCode":"ن-۲۲","SentDateTime":"۱۳۹۸/۰۹/۰۳ ۱۴:۳۰:۴۸","PublishDateTime":"۱۳۹۸/۰۹/۰۳ ۱۴:۳۰:۴۸","HasHtml":true,"Url":"/Reports/Decision.aspx?LetterSerial=cSxbgSKt2OcZgIKLFtInlA%3D%3D&rt=0&let=147&ct=0&ft=-1","HasExcel":false,"HasPdf":true,"HasXbrl":false,"HasAttachment":true,"AttachmentUrl":"/Reports/Attachment.aspx?LetterSerial=cSxbgSKt2OcZgIKLFtInlA%3d%3d","PdfUrl":"DownloadFile.aspx?hs=cSxbgSKt2OcZgIKLFtInlA%3d%3d&ft=1005&let=147","ExcelUrl":"","XbrlUrl":"","TedanUrl":"http://www.tedan.ir"},{"SuperVision":{"UnderSupervision":0,"AdditionalInfo":"","Reasons":[]},"TracingNo":586695,"Symbol":"پتایر","CompanyName":"تولیدی ایران تایر","UnderSupervision":0,"Title":"گزارش فعالیت ماهانه دوره ۱ ماهه منتهی به ۱۳۹۸/۰۸/۳۰","LetterCode":"ن-۳۰","SentDateTime":"۱۳۹۸/۰۹/۰۳ ۱۴:۳۰:۴۲","PublishDateTime":"۱۳۹۸/۰۹/۰۳ ۱۴:۳۰:۴۲","HasHtml":true,"Url":"/Reports/Decision.aspx?LetterSerial=W7qSPJNbPWFyoXuHnWpD%2Bg%3D%3D&rt=0&let=58&ct=0&ft=-1","HasExcel":true,"HasPdf":true,"HasXbrl":false,"HasAttachment":false,"AttachmentUrl":"","PdfUrl":"DownloadFile.aspx?hs=W7qSPJNbPWFyoXuHnWpD%2bg%3d%3d&ft=1005&let=58","ExcelUrl":"https://excel.codal.ir/service/Excel/GetAll/W7qSPJNbPWFyoXuHnWpD%2bg%3d%3d/0","XbrlUrl":"","TedanUrl":"http://www.tedan.ir"},{"SuperVision":{"UnderSupervision":0,"AdditionalInfo":"","Reasons":[]},"TracingNo":586883,"Symbol":"ولبهمن","CompanyName":"بهمن لیزینگ","UnderSupervision":0,"Title":"گزارش فعالیت ماهانه دوره ۱ ماهه منتهی به ۱۳۹۸/۰۸/۳۰","LetterCode":"ن-۳۰","SentDateTime":"۱۳۹۸/۰۹/۰۳ ۱۴:۲۸:۰۶","PublishDateTime":"۱۳۹۸/۰۹/۰۳ ۱۴:۲۸:۰۶","HasHtml":true,"Url":"/Reports/Decision.aspx?LetterSerial=yHGuhcRfadhoXOtyFm9IMg%3D%3D&rt=4&let=58&ct=0&ft=-1","HasExcel":true,"HasPdf":true,"HasXbrl":false,"HasAttachment":true,"AttachmentUrl":"/Reports/Attachment.aspx?LetterSerial=yHGuhcRfadhoXOtyFm9IMg%3d%3d","PdfUrl":"DownloadFile.aspx?hs=yHGuhcRfadhoXOtyFm9IMg%3d%3d&ft=1005&let=58","ExcelUrl":"https://excel.codal.ir/service/Excel/GetAll/yHGuhcRfadhoXOtyFm9IMg%3d%3d/0","XbrlUrl":"","TedanUrl":"http://www.tedan.ir"},{"SuperVision":{"UnderSupervision":0,"AdditionalInfo":"","Reasons":[]},"TracingNo":586381,"Symbol":"وپاسار","CompanyName":"بانک پاسارگاد","UnderSupervision":0,"Title":"اطلاعات و صورت‌های مالی میاندوره‌ای  دوره ۶ ماهه منتهی به ۱۳۹۸/۰۵/۳۱ (حسابرسی شده) (شرکت زیر ساخت فناوری اطلاعات و ارتباطات پاسارگاد آریان)","LetterCode":"ن-۱۰","SentDateTime":"۱۳۹۸/۰۹/۰۳ ۱۴:۲۶:۳۸","PublishDateTime":"۱۳۹۸/۰۹/۰۳ ۱۴:۲۶:۳۸","HasHtml":true,"Url":"/Reports/Decision.aspx?LetterSerial=JzIv0ts8DkLweznw4QQQaQQQ%2BAPA%3D%3D&rt=5&let=6&ct=0&ft=-1","HasExcel":true,"HasPdf":true,"HasXbrl":false,"HasAttachment":true,"AttachmentUrl":"/Reports/Attachment.aspx?LetterSerial=JzIv0ts8DkLweznw4QQQaQQQ%2bAPA%3d%3d","PdfUrl":"DownloadFile.aspx?hs=JzIv0ts8DkLweznw4QQQaQQQ%2bAPA%3d%3d&ft=1005&let=6","ExcelUrl":"https://excel.codal.ir/service/Excel/GetAll/JzIv0ts8DkLweznw4QQQaQQQ%2bAPA%3d%3d/0","XbrlUrl":"","TedanUrl":"http://www.tedan.ir"},{"SuperVision":{"UnderSupervision":0,"AdditionalInfo":"","Reasons":[]},"TracingNo":586829,"Symbol":"زمگسا","CompanyName":"کشاورزی و دامپروری مگسال","UnderSupervision":0,"Title":"آگهی ثبت تصمیمات مجمع عادی سالیانه دوره ۱۲ ماهه منتهی به ۱۳۹۷/۱۲/۲۹","LetterCode":"ن-۴۲","SentDateTime":"۱۳۹۸/۰۹/۰۳ ۱۴:۲۱:۳۵","PublishDateTime":"۱۳۹۸/۰۹/۰۳ ۱۴:۲۱:۳۵","HasHtml":false,"Url":"/Reports/Attachment.aspx?LetterSerial=bALqQQQaQQQuCQlCtKoSQQQaQQQxbTJUbQ%3d%3d","HasExcel":false,"HasPdf":false,"HasXbrl":false,"HasAttachment":true,"AttachmentUrl":"/Reports/Attachment.aspx?LetterSerial=bALqQQQaQQQuCQlCtKoSQQQaQQQxbTJUbQ%3d%3d","PdfUrl":"","ExcelUrl":"","XbrlUrl":"","TedanUrl":"http://www.tedan.ir"},{"SuperVision":{"UnderSupervision":0,"AdditionalInfo":"","Reasons":[]},"TracingNo":586875,"Symbol":"فنورد","CompanyName":"نورد و تولید قطعات فولادی","UnderSupervision":0,"Title":"شفاف سازی در خصوص نوسان قیمت سهام","LetterCode":"ن-۲۲","SentDateTime":"۱۳۹۸/۰۹/۰۳ ۱۴:۱۷:۴۵","PublishDateTime":"۱۳۹۸/۰۹/۰۳ ۱۴:۱۷:۴۵","HasHtml":true,"Url":"/Reports/Decision.aspx?LetterSerial=2G5qInjXF3Faoxn1CJQhrQ%3D%3D&rt=0&let=147&ct=0&ft=-1","HasExcel":false,"HasPdf":true,"HasXbrl":false,"HasAttachment":false,"AttachmentUrl":"","PdfUrl":"DownloadFile.aspx?hs=2G5qInjXF3Faoxn1CJQhrQ%3d%3d&ft=1005&let=147","ExcelUrl":"","XbrlUrl":"","TedanUrl":"http://www.tedan.ir"},{"SuperVision":{"UnderSupervision":0,"AdditionalInfo":"","Reasons":[]},"TracingNo":586849,"Symbol":"امید بازار","CompanyName":"صندوق سرمایه گذاری بازارگردان امید ایرانیان(بازارگردانی)","UnderSupervision":0,"Title":"تصمیمات مجمع صندوق سرمایه گذاری","LetterCode":"","SentDateTime":"۱۳۹۸/۰۹/۰۳ ۱۴:۰۸:۱۷","PublishDateTime":"۱۳۹۸/۰۹/۰۳ ۱۴:۰۸:۱۷","HasHtml":true,"Url":"/Reports/Decision.aspx?LetterSerial=LkYOMQQQaQQQhNkkWkeYU9DWzB3g%3D%3D&rt=2&let=122&ct=5&ft=7","HasExcel":false,"HasPdf":true,"HasXbrl":false,"HasAttachment":true,"AttachmentUrl":"/Reports/Attachment.aspx?LetterSerial=LkYOMQQQaQQQhNkkWkeYU9DWzB3g%3d%3d","PdfUrl":"DownloadFile.aspx?hs=LkYOMQQQaQQQhNkkWkeYU9DWzB3g%3d%3d&ft=1005&let=122","ExcelUrl":"","XbrlUrl":"","TedanUrl":"http://www.tedan.ir"},{"SuperVision":{"UnderSupervision":1,"AdditionalInfo":"","Reasons":["عدم ارائه صورت‌های مالی ۱۲ ماهه حسابرسی شدۀ شرکت اصلی و تلفیقی گروه","عدم ارائه گزارش هیئت‌مدیره به مجمع و اظهارنظر حسابرس در مورد آن","عدم ارائه گزارش تفسیری مدیریت ۱۲ ماهه حسابرسی شده"]},"TracingNo":586848,"Symbol":"کساوه","CompanyName":"صنایع کاشی و سرامیک سینا","UnderSupervision":0,"Title":"گزارش فعالیت ماهانه دوره ۱ ماهه منتهی به ۱۳۹۸/۰۸/۳۰","LetterCode":"ن-۳۰","SentDateTime":"۱۳۹۸/۰۹/۰۳ ۱۳:۵۸:۱۶","PublishDateTime":"۱۳۹۸/۰۹/۰۳ ۱۳:۵۸:۱۶","HasHtml":true,"Url":"/Reports/Decision.aspx?LetterSerial=wrBfjFTIUK9XLee4CkR2bA%3D%3D&rt=0&let=58&ct=0&ft=-1","HasExcel":true,"HasPdf":true,"HasXbrl":false,"HasAttachment":false,"AttachmentUrl":"","PdfUrl":"DownloadFile.aspx?hs=wrBfjFTIUK9XLee4CkR2bA%3d%3d&ft=1005&let=58","ExcelUrl":"https://excel.codal.ir/service/Excel/GetAll/wrBfjFTIUK9XLee4CkR2bA%3d%3d/0","XbrlUrl":"","TedanUrl":"http://www.tedan.ir"},{"SuperVision":{"UnderSupervision":0,"AdditionalInfo":"","Reasons":[]},"TracingNo":586859,"Symbol":"زرین سهام","CompanyName":"صندوق سرمایه گذاری زرین پارسیان","UnderSupervision":0,"Title":"صورت وضعیت پورتفوی صندوق سرمایه گذاری دوره ۱ ماهه منتهی به ۱۳۹۸/۰۸/۳۰","LetterCode":"","SentDateTime":"۱۳۹۸/۰۹/۰۳ ۱۳:۵۶:۵۲","PublishDateTime":"۱۳۹۸/۰۹/۰۳ ۱۳:۵۶:۵۲","HasHtml":false,"Url":"/Reports/Attachment.aspx?LetterSerial=Kz4y9GeLRbSCnYN2ezwWNQ%3d%3d","HasExcel":false,"HasPdf":false,"HasXbrl":false,"HasAttachment":true,"AttachmentUrl":"/Reports/Attachment.aspx?LetterSerial=Kz4y9GeLRbSCnYN2ezwWNQ%3d%3d","PdfUrl":"","ExcelUrl":"","XbrlUrl":"","TedanUrl":"http://www.tedan.ir"},{"SuperVision":{"UnderSupervision":0,"AdditionalInfo":"","Reasons":[]},"TracingNo":586040,"Symbol":"ساینا","CompanyName":"صنایع بهداشتی ساینا","UnderSupervision":0,"Title":"گزارش فعالیت ماهانه دوره ۱ ماهه منتهی به ۱۳۹۸/۰۸/۳۰","LetterCode":"ن-۳۰","SentDateTime":"۱۳۹۸/۰۹/۰۳ ۱۳:۵۶:۴۷","PublishDateTime":"۱۳۹۸/۰۹/۰۳ ۱۳:۵۶:۴۷","HasHtml":true,"Url":"/Reports/Decision.aspx?LetterSerial=vtwjPqGJviOBVx8426KF1g%3D%3D&rt=0&let=58&ct=0&ft=-1","HasExcel":true,"HasPdf":true,"HasXbrl":false,"HasAttachment":false,"AttachmentUrl":"","PdfUrl":"DownloadFile.aspx?hs=vtwjPqGJviOBVx8426KF1g%3d%3d&ft=1005&let=58","ExcelUrl":"https://excel.codal.ir/service/Excel/GetAll/vtwjPqGJviOBVx8426KF1g%3d%3d/0","XbrlUrl":"","TedanUrl":"http://www.tedan.ir"}]}