{"Total":15679,"Page":784,"Letters":[{"SuperVision":{"UnderSupervision":0,"AdditionalInfo":"","Reasons":[]},"TracingNo":203198,"Symbol":"ونیکی","CompanyName":"سرمایه گذاری ملی ایران","UnderSupervision":0,"Title":"تصمیمات مجمع عمومی عادی سالیانه دوره ۱۲ ماهه منتهی به ۱۳۹۳/۰۹/۳۰","LetterCode":"ن-۵۲","SentDateTime":"۱۳۹۳/۱۲/۲۴ ۱۶:۴۲:۵۰","PublishDateTime":"۱۳۹۳/۱۲/۲۴ ۱۶:۴۲:۵۰","HasHtml":true,"Url":"/Reports/Decision.aspx?LetterSerial=QR5kUjx4ZfLA4s%2biC8lRAA%3d%3d&rt=2&let=20","HasExcel":false,"HasPdf":true,"HasXbrl":false,"HasAttachment":true,"AttachmentUrl":"/Reports/Attachment.aspx?LetterSerial=QR5kUjx4ZfLA4s%2biC8lRAA%3d%3d","PdfUrl":"DownloadFile.aspx?hs=QR5kUjx4ZfLA4s%2biC8lRAA%3d%3d&ft=1005&let=20","ExcelUrl":"","XbrlUrl":"","TedanUrl":"http://www.tedan.ir"},{"SuperVision":{"UnderSupervision":0,"AdditionalInfo":"","Reasons":[]},"TracingNo":199964,"Symbol":"دکیمی","CompanyName":"کیمیدارو","UnderSupervision":0,"Title":"اولین پیش بینی درآمد هر سهم سال مالی منتهی به ۱۳۹۴/۱۲/۲۹ (حسابرسی شده)","LetterCode":"","SentDateTime":"۱۳۹۳/۱۲/۲۳ ۱۳:۵۰:۵۹","PublishDateTime":"۱۳۹۳/۱۲/۲۴ ۱۶:۲۱:۵۳","HasHtml":true,"Url":"/Reports/Decision.aspx?LetterSerial=KteNimVKYCwN7Go6g47HmA%3d%3d&rt=0&let=1","HasExcel":true,"HasPdf":true,"HasXbrl":false,"HasAttachment":true,"AttachmentUrl":"/Reports/Attachment.aspx?LetterSerial=KteNimVKYCwN7Go6g47HmA%3d%3d","PdfUrl":"DownloadFile.aspx?hs=KteNimVKYCwN7Go6g47HmA%3d%3d&ft=1005&let=1","ExcelUrl":"https://excel.codal.ir/service/Excel/GetAll/KteNimVKYCwN7Go6g47HmA%3d%3d/0","XbrlUrl":"","TedanUrl":"http://www.tedan.ir"},{"SuperVision":{"UnderSupervision":0,"AdditionalInfo":"","Reasons":[]},"TracingNo":203483,"Symbol":"صندوق سرمایه گذاری مشترک یکم اکسیر فارابی","CompanyName":"صندوق سرمایه گذاری مشترک یکم اکسیر فارابی","UnderSupervision":0,"Title":"نامه ها و گزارش های نهادهای مالی دوره ۳ ماهه منتهی به ۱۳۹۳/۱۱/۲۶","LetterCode":"","SentDateTime":"۱۳۹۳/۱۲/۲۴ ۱۵:۱۱:۵۷","PublishDateTime":"۱۳۹۳/۱۲/۲۴ ۱۶:۲۰:۱۳","HasHtml":false,"Url":"/Reports/Attachment.aspx?LetterSerial=yqrt8uTqwUqzABAJ8ZOB8w%3d%3d","HasExcel":false,"HasPdf":false,"HasXbrl":false,"HasAttachment":true,"AttachmentUrl":"/Reports/Attachment.aspx?LetterSerial=yqrt8uTqwUqzABAJ8ZOB8w%3d%3d","PdfUrl":"","ExcelUrl":"","XbrlUrl":"","TedanUrl":"http://www.tedan.ir"},{"SuperVision":{"UnderSupervision":1,"AdditionalInfo":"","Reasons":["عدم ارائه صورت‌های مالی ۱۲ ماهه حسابرسی شدۀ شرکت اصلی و تلفیقی گروه","عدم ارائه گزارش تفسیری مدیریت ۱۲ ماهه حسابرسی شده"]},"TracingNo":199677,"Symbol":"حپترو","CompanyName":"مهندسی حمل و نقل پتروشیمی","UnderSupervision":0,"Title":"اولین پیش بینی درآمد هر سهم سال مالی منتهی به ۱۳۹۴/۱۲/۲۹ (حسابرسی شده)","LetterCode":"","SentDateTime":"۱۳۹۳/۱۲/۲۳ ۱۴:۳۷:۳۲","PublishDateTime":"۱۳۹۳/۱۲/۲۴ ۱۶:۱۹:۱۳","HasHtml":true,"Url":"/Reports/Decision.aspx?LetterSerial=ZYPDRJ3NVRzn36P7SgsEWw%3d%3d&rt=5&let=1","HasExcel":true,"HasPdf":true,"HasXbrl":false,"HasAttachment":true,"AttachmentUrl":"/Reports/Attachment.aspx?LetterSerial=ZYPDRJ3NVRzn36P7SgsEWw%3d%3d","PdfUrl":"DownloadFile.aspx?hs=ZYPDRJ3NVRzn36P7SgsEWw%3d%3d&ft=1005&let=1","ExcelUrl":"https://excel.codal.ir/service/Excel/GetAll/ZYPDRJ3NVRzn36P7SgsEWw%3d%3d/0","XbrlUrl":"","TedanUrl":"http://www.tedan.ir"},{"SuperVision":{"UnderSupervision":0,"AdditionalInfo":"","Reasons":[]},"TracingNo":203494,"Symbol":"کایگچ","CompanyName":"ایران گچ","UnderSupervision":0,"Title":"تصمیمات مجمع عمومی عادی سالیانه دوره ۱۲ ماهه منتهی به ۱۳۹۳/۱۰/۱۰","LetterCode":"ن-۵۲","SentDateTime":"۱۳۹۳/۱۲/۲۴ ۱۶:۱۲:۰۷","PublishDateTime":"۱۳۹۳/۱۲/۲۴ ۱۶:۱۲:۰۷","HasHtml":true,"Url":"/Reports/Decision.aspx?LetterSerial=4KLGcIXNG1DfDj0P8%2fepmw%3d%3d&rt=0&let=20","HasExcel":false,"HasPdf":true,"HasXbrl":false,"HasAttachment":true,"AttachmentUrl":"/Reports/Attachment.aspx?LetterSerial=4KLGcIXNG1DfDj0P8QQQaQQQepmw%3d%3d","PdfUrl":"DownloadFile.aspx?hs=4KLGcIXNG1DfDj0P8QQQaQQQepmw%3d%3d&ft=1005&let=20","ExcelUrl":"","XbrlUrl":"","TedanUrl":"http://www.tedan.ir"},{"SuperVision":{"UnderSupervision":0,"AdditionalInfo":"","Reasons":[]},"TracingNo":199639,"Symbol":"قپیرا","CompanyName":"فرآورده های غذایی و قند پیرانشهر","UnderSupervision":0,"Title":"پیش بینی درآمد هر سهم سال مالی منتهی به ۱۳۹۴/۰۴/۳۱ بر اساس عملکرد واقعی دوره ۶ ماهه  (حسابرسی شده)","LetterCode":"","SentDateTime":"۱۳۹۳/۱۲/۲۳ ۱۹:۵۶:۴۷","PublishDateTime":"۱۳۹۳/۱۲/۲۴ ۱۶:۰۵:۴۷","HasHtml":true,"Url":"/Reports/Decision.aspx?LetterSerial=dSB3VRruGVZBNYQT%2bgJojg%3d%3d&rt=0&let=2","HasExcel":true,"HasPdf":true,"HasXbrl":false,"HasAttachment":true,"AttachmentUrl":"/Reports/Attachment.aspx?LetterSerial=dSB3VRruGVZBNYQT%2bgJojg%3d%3d","PdfUrl":"DownloadFile.aspx?hs=dSB3VRruGVZBNYQT%2bgJojg%3d%3d&ft=1005&let=2","ExcelUrl":"https://excel.codal.ir/service/Excel/GetAll/dSB3VRruGVZBNYQT%2bgJojg%3d%3d/0","XbrlUrl":"","TedanUrl":"http://www.tedan.ir"},{"SuperVision":{"UnderSupervision":0,"AdditionalInfo":"","Reasons":[]},"TracingNo":203501,"Symbol":"ثاخت","CompanyName":"بین المللی توسعه ساختمان","UnderSupervision":0,"Title":"معرفی یا تغییر در ترکیب اعضای هیئت‌مدیره","LetterCode":"ن-۴۵","SentDateTime":"۱۳۹۳/۱۲/۲۴ ۱۵:۵۹:۵۹","PublishDateTime":"۱۳۹۳/۱۲/۲۴ ۱۵:۵۹:۵۹","HasHtml":true,"Url":"/Reports/Decision.aspx?LetterSerial=o3jVBZ7UJgJRf4l%2f6vZTag%3d%3d&rt=1&let=19","HasExcel":false,"HasPdf":true,"HasXbrl":false,"HasAttachment":false,"AttachmentUrl":"","PdfUrl":"DownloadFile.aspx?hs=o3jVBZ7UJgJRf4lQQQaQQQ6vZTag%3d%3d&ft=1005&let=19","ExcelUrl":"","XbrlUrl":"","TedanUrl":"http://www.tedan.ir"},{"SuperVision":{"UnderSupervision":0,"AdditionalInfo":"","Reasons":[]},"TracingNo":203157,"Symbol":"آسیا","CompanyName":"بیمه آسیا","UnderSupervision":0,"Title":"اولین پیش بینی سود هر سهم برای سال مالی منتهی به ۱۳۹۴/۱۲/۲۹ (حسابرسی شده ) (به پیوست) ","LetterCode":"","SentDateTime":"۱۳۹۳/۱۲/۲۱ ۱۳:۰۹:۲۸","PublishDateTime":"۱۳۹۳/۱۲/۲۴ ۱۵:۵۸:۲۹","HasHtml":false,"Url":"/Reports/Attachment.aspx?LetterSerial=V3Sk64XQQQaQQQGIgnwjpf%2b8SL9A%3d%3d","HasExcel":false,"HasPdf":false,"HasXbrl":false,"HasAttachment":true,"AttachmentUrl":"/Reports/Attachment.aspx?LetterSerial=V3Sk64XQQQaQQQGIgnwjpf%2b8SL9A%3d%3d","PdfUrl":"","ExcelUrl":"","XbrlUrl":"","TedanUrl":"http://www.tedan.ir"},{"SuperVision":{"UnderSupervision":0,"AdditionalInfo":"","Reasons":[]},"TracingNo":203208,"Symbol":"ونیکی","CompanyName":"سرمایه گذاری ملی ایران","UnderSupervision":0,"Title":"تصمیمات مجمع عمومی فوق‌العاده دوره ۱۲ ماهه منتهی به ۱۳۹۳/۰۹/۳۰","LetterCode":"ن-۵۷","SentDateTime":"۱۳۹۳/۱۲/۲۴ ۱۵:۳۸:۵۶","PublishDateTime":"۱۳۹۳/۱۲/۲۴ ۱۵:۳۸:۵۶","HasHtml":true,"Url":"/Reports/Decision.aspx?LetterSerial=G9SM7fJSNsw4opU5PEh42Q%3d%3d&rt=2&let=22","HasExcel":false,"HasPdf":true,"HasXbrl":false,"HasAttachment":true,"AttachmentUrl":"/Reports/Attachment.aspx?LetterSerial=G9SM7fJSNsw4opU5PEh42Q%3d%3d","PdfUrl":"DownloadFile.aspx?hs=G9SM7fJSNsw4opU5PEh42Q%3d%3d&ft=1005&let=22","ExcelUrl":"","XbrlUrl":"","TedanUrl":"http://www.tedan.ir"},{"SuperVision":{"UnderSupervision":0,"AdditionalInfo":"","Reasons":[]},"TracingNo":203497,"Symbol":"فلات","CompanyName":"گروه سرمایه گذاری صنایع و معادن فلات ایرانیان","UnderSupervision":0,"Title":"گزارش فعالیت هیئت مدیره دوره ۱۲ ماهه منتهی به ۱۳۹۳/۰۹/۳۰","LetterCode":"ن-۱۱","SentDateTime":"۱۳۹۳/۱۲/۲۴ ۱۵:۳۵:۳۹","PublishDateTime":"۱۳۹۳/۱۲/۲۴ ۱۵:۳۵:۳۹","HasHtml":false,"Url":"/Reports/Attachment.aspx?LetterSerial=Yhg84oo5WWvBZVcXzvRnmQ%3d%3d","HasExcel":false,"HasPdf":false,"HasXbrl":false,"HasAttachment":true,"AttachmentUrl":"/Reports/Attachment.aspx?LetterSerial=Yhg84oo5WWvBZVcXzvRnmQ%3d%3d","PdfUrl":"","ExcelUrl":"","XbrlUrl":"","TedanUrl":"http://www.tedan.ir"},{"SuperVision":{"UnderSupervision":0,"AdditionalInfo":"","Reasons":[]},"TracingNo":203313,"Symbol":"قنقش","CompanyName":"قند نقش جهان","UnderSupervision":0,"Title":"اولین پیش بینی درآمد هر سهم سال مالی منتهی به ۱۳۹۴/۱۲/۲۹ (حسابرسی شده)","LetterCode":"","SentDateTime":"۱۳۹۳/۱۲/۲۴ ۱۴:۴۴:۵۰","PublishDateTime":"۱۳۹۳/۱۲/۲۴ ۱۴:۴۴:۵۰","HasHtml":true,"Url":"/Reports/Decision.aspx?LetterSerial=KteBkuDeWGjPl9346zmkPQ%3d%3d&rt=0&let=1","HasExcel":true,"HasPdf":true,"HasXbrl":false,"HasAttachment":true,"AttachmentUrl":"/Reports/Attachment.aspx?LetterSerial=KteBkuDeWGjPl9346zmkPQ%3d%3d","PdfUrl":"DownloadFile.aspx?hs=KteBkuDeWGjPl9346zmkPQ%3d%3d&ft=1005&let=1","ExcelUrl":"https://excel.codal.ir/service/Excel/GetAll/KteBkuDeWGjPl9346zmkPQ%3d%3d/0","XbrlUrl":"","TedanUrl":"http://www.tedan.ir"},{"SuperVision":{"UnderSupervision":0,"AdditionalInfo":"","Reasons":[]},"TracingNo":199631,"Symbol":"قپیرا","CompanyName":"فرآورده های غذایی و قند پیرانشهر","UnderSupervision":0,"Title":"اطلاعات و صورتهای مالی میاندوره ای دوره ۶ ماهه منتهی به ۱۳۹۳/۱۰/۳۰(حسابرسی شده)","LetterCode":"ن-۱۰","SentDateTime":"۱۳۹۳/۱۲/۲۴ ۱۴:۱۱:۰۲","PublishDateTime":"۱۳۹۳/۱۲/۲۴ ۱۴:۱۱:۰۲","HasHtml":true,"Url":"/Reports/Decision.aspx?LetterSerial=NnM5kOOF6RdJfgxJSFbddQ%3d%3d&rt=0&let=6","HasExcel":true,"HasPdf":true,"HasXbrl":false,"HasAttachment":true,"AttachmentUrl":"/Reports/Attachment.aspx?LetterSerial=NnM5kOOF6RdJfgxJSFbddQ%3d%3d","PdfUrl":"DownloadFile.aspx?hs=NnM5kOOF6RdJfgxJSFbddQ%3d%3d&ft=1005&let=6","ExcelUrl":"https://excel.codal.ir/service/Excel/GetAll/NnM5kOOF6RdJfgxJSFbddQ%3d%3d/0","XbrlUrl":"","TedanUrl":"http://www.tedan.ir"},{"SuperVision":{"UnderSupervision":0,"AdditionalInfo":"","Reasons":[]},"TracingNo":185233,"Symbol":"شراز","CompanyName":"پالایش نفت شیراز","UnderSupervision":0,"Title":"معرفی یا تغییر در ترکیب اعضای هیئت‌مدیره","LetterCode":"ن-۴۵","SentDateTime":"۱۳۹۳/۱۲/۲۴ ۱۴:۰۱:۵۹","PublishDateTime":"۱۳۹۳/۱۲/۲۴ ۱۴:۰۱:۵۹","HasHtml":true,"Url":"/Reports/Decision.aspx?LetterSerial=vk5sw8EcP7twYDY9eKA3%2fw%3d%3d&rt=0&let=19","HasExcel":false,"HasPdf":true,"HasXbrl":false,"HasAttachment":true,"AttachmentUrl":"/Reports/Attachment.aspx?LetterSerial=vk5sw8EcP7twYDY9eKA3QQQaQQQw%3d%3d","PdfUrl":"DownloadFile.aspx?hs=vk5sw8EcP7twYDY9eKA3QQQaQQQw%3d%3d&ft=1005&let=19","ExcelUrl":"","XbrlUrl":"","TedanUrl":"http://www.tedan.ir"},{"SuperVision":{"UnderSupervision":3,"AdditionalInfo":"","Reasons":["نیاز به بررسی وضعیت شفافیت اطلاعاتی ناشر"]},"TracingNo":203462,"Symbol":"دهدشت","CompanyName":"صنایع پتروشیمی دهدشت","UnderSupervision":0,"Title":"تصمیمات مجمع عمومی عادی به‌طور فوق‌العاده دوره ۱۲ ماهه منتهی به ۱۳۹۴/۰۶/۳۱(اصلاحیه)","LetterCode":"ن-۵۵","SentDateTime":"۱۳۹۳/۱۲/۲۴ ۱۳:۴۶:۵۶","PublishDateTime":"۱۳۹۳/۱۲/۲۴ ۱۳:۴۶:۵۶","HasHtml":true,"Url":"/Reports/Decision.aspx?LetterSerial=s5j%2badh%2fOqpisJg0maKR6g%3d%3d&rt=0&let=21","HasExcel":false,"HasPdf":true,"HasXbrl":false,"HasAttachment":true,"AttachmentUrl":"/Reports/Attachment.aspx?LetterSerial=s5j%2badhQQQaQQQOqpisJg0maKR6g%3d%3d","PdfUrl":"DownloadFile.aspx?hs=s5j%2badhQQQaQQQOqpisJg0maKR6g%3d%3d&ft=1005&let=21","ExcelUrl":"","XbrlUrl":"","TedanUrl":"http://www.tedan.ir"},{"SuperVision":{"UnderSupervision":3,"AdditionalInfo":"","Reasons":["نیاز به بررسی وضعیت شفافیت اطلاعاتی ناشر"]},"TracingNo":203458,"Symbol":"دهدشت","CompanyName":"صنایع پتروشیمی دهدشت","UnderSupervision":0,"Title":"تصمیمات مجمع عمومی فوق‌العاده دوره ۱۲ ماهه منتهی به ۱۳۹۴/۰۶/۳۱(اصلاحیه)","LetterCode":"ن-۵۷","SentDateTime":"۱۳۹۳/۱۲/۲۴ ۱۳:۳۱:۱۷","PublishDateTime":"۱۳۹۳/۱۲/۲۴ ۱۳:۳۱:۱۷","HasHtml":true,"Url":"/Reports/Decision.aspx?LetterSerial=26XyJDJqXcXYyrXbx92BBw%3d%3d&rt=0&let=22","HasExcel":false,"HasPdf":true,"HasXbrl":false,"HasAttachment":true,"AttachmentUrl":"/Reports/Attachment.aspx?LetterSerial=26XyJDJqXcXYyrXbx92BBw%3d%3d","PdfUrl":"DownloadFile.aspx?hs=26XyJDJqXcXYyrXbx92BBw%3d%3d&ft=1005&let=22","ExcelUrl":"","XbrlUrl":"","TedanUrl":"http://www.tedan.ir"},{"SuperVision":{"UnderSupervision":0,"AdditionalInfo":"","Reasons":[]},"TracingNo":203455,"Symbol":"ومعادن","CompanyName":"سرمایه گذاری توسعه معادن و فلزات","UnderSupervision":0,"Title":"تصمیمات مجمع عمومی فوق‌العاده دوره ۱۲ ماهه منتهی به ۱۳۹۳/۱۲/۲۹","LetterCode":"ن-۵۷","SentDateTime":"۱۳۹۳/۱۲/۲۴ ۱۳:۱۸:۲۹","PublishDateTime":"۱۳۹۳/۱۲/۲۴ ۱۳:۱۸:۲۹","HasHtml":true,"Url":"/Reports/Decision.aspx?LetterSerial=2AKQq0Zf%2bNC4iB7OVaEtTg%3d%3d&rt=2&let=22","HasExcel":false,"HasPdf":true,"HasXbrl":false,"HasAttachment":true,"AttachmentUrl":"/Reports/Attachment.aspx?LetterSerial=2AKQq0Zf%2bNC4iB7OVaEtTg%3d%3d","PdfUrl":"DownloadFile.aspx?hs=2AKQq0Zf%2bNC4iB7OVaEtTg%3d%3d&ft=1005&let=22","ExcelUrl":"","XbrlUrl":"","TedanUrl":"http://www.tedan.ir"},{"SuperVision":{"UnderSupervision":0,"AdditionalInfo":"","Reasons":[]},"TracingNo":203453,"Symbol":"ومعادن","CompanyName":"سرمایه گذاری توسعه معادن و فلزات","UnderSupervision":0,"Title":"آگهی دعوت به مجمع عمومی فوق العاده دوره ۱۲ ماهه منتهی به ۱۳۹۳/۱۲/۲۹(اصلاحیه)","LetterCode":"ن-۵۶","SentDateTime":"۱۳۹۳/۱۲/۲۴ ۱۲:۵۸:۵۸","PublishDateTime":"۱۳۹۳/۱۲/۲۴ ۱۲:۵۸:۵۸","HasHtml":true,"Url":"/Reports/Decision.aspx?LetterSerial=ZpTFKPbbJICeeIqTNnc4vA%3d%3d&rt=2&let=18","HasExcel":false,"HasPdf":true,"HasXbrl":false,"HasAttachment":true,"AttachmentUrl":"/Reports/Attachment.aspx?LetterSerial=ZpTFKPbbJICeeIqTNnc4vA%3d%3d","PdfUrl":"DownloadFile.aspx?hs=ZpTFKPbbJICeeIqTNnc4vA%3d%3d&ft=1005&let=18","ExcelUrl":"","XbrlUrl":"","TedanUrl":"http://www.tedan.ir"},{"SuperVision":{"UnderSupervision":3,"AdditionalInfo":"","Reasons":["نیاز به بررسی وضعیت شفافیت اطلاعاتی ناشر"]},"TracingNo":203438,"Symbol":"دهدشت","CompanyName":"صنایع پتروشیمی دهدشت","UnderSupervision":0,"Title":"تصمیمات مجمع عمومی عادی به‌طور فوق‌العاده دوره ۱۲ ماهه منتهی به ۱۳۹۴/۰۶/۳۱","LetterCode":"ن-۵۵","SentDateTime":"۱۳۹۳/۱۲/۲۴ ۱۲:۱۴:۱۴","PublishDateTime":"۱۳۹۳/۱۲/۲۴ ۱۲:۱۴:۱۴","HasHtml":true,"Url":"/Reports/Decision.aspx?LetterSerial=UK%2fca%2fRPpKlhYhJ7UkdIIA%3d%3d&rt=0&let=21","HasExcel":false,"HasPdf":true,"HasXbrl":false,"HasAttachment":true,"AttachmentUrl":"/Reports/Attachment.aspx?LetterSerial=UKQQQaQQQcaQQQaQQQRPpKlhYhJ7UkdIIA%3d%3d","PdfUrl":"DownloadFile.aspx?hs=UKQQQaQQQcaQQQaQQQRPpKlhYhJ7UkdIIA%3d%3d&ft=1005&let=21","ExcelUrl":"","XbrlUrl":"","TedanUrl":"http://www.tedan.ir"},{"SuperVision":{"UnderSupervision":3,"AdditionalInfo":"","Reasons":["نیاز به بررسی وضعیت شفافیت اطلاعاتی ناشر"]},"TracingNo":203439,"Symbol":"دهدشت","CompanyName":"صنایع پتروشیمی دهدشت","UnderSupervision":0,"Title":"تصمیمات مجمع عمومی فوق‌العاده دوره ۱۲ ماهه منتهی به ۱۳۹۴/۰۶/۳۱","LetterCode":"ن-۵۷","SentDateTime":"۱۳۹۳/۱۲/۲۴ ۱۲:۰۱:۴۵","PublishDateTime":"۱۳۹۳/۱۲/۲۴ ۱۲:۰۱:۴۵","HasHtml":true,"Url":"/Reports/Decision.aspx?LetterSerial=M%2f7m4dU2zCN2JnvpK5K6%2fA%3d%3d&rt=0&let=22","HasExcel":false,"HasPdf":true,"HasXbrl":false,"HasAttachment":true,"AttachmentUrl":"/Reports/Attachment.aspx?LetterSerial=MQQQaQQQ7m4dU2zCN2JnvpK5K6QQQaQQQA%3d%3d","PdfUrl":"DownloadFile.aspx?hs=MQQQaQQQ7m4dU2zCN2JnvpK5K6QQQaQQQA%3d%3d&ft=1005&let=22","ExcelUrl":"","XbrlUrl":"","TedanUrl":"http://www.tedan.ir"},{"SuperVision":{"UnderSupervision":0,"AdditionalInfo":"","Reasons":[]},"TracingNo":201131,"Symbol":"کگاز","CompanyName":"شیشه و گاز","UnderSupervision":0,"Title":"اطلاعات و صورتهای مالی میاندوره ای دوره ۶ ماهه منتهی به ۱۳۹۳/۰۶/۳۱(حسابرسی شده)","LetterCode":"ن-۱۰","SentDateTime":"۱۳۹۳/۱۲/۲۰ ۱۸:۱۷:۲۷","PublishDateTime":"۱۳۹۳/۱۲/۲۴ ۱۱:۴۶:۲۱","HasHtml":true,"Url":"/Reports/Decision.aspx?LetterSerial=wjNDK08XHXRbtxi9kmkBXg%3d%3d&rt=0&let=6","HasExcel":true,"HasPdf":true,"HasXbrl":false,"HasAttachment":true,"AttachmentUrl":"/Reports/Attachment.aspx?LetterSerial=wjNDK08XHXRbtxi9kmkBXg%3d%3d","PdfUrl":"DownloadFile.aspx?hs=wjNDK08XHXRbtxi9kmkBXg%3d%3d&ft=1005&let=6","ExcelUrl":"https://excel.codal.ir/service/Excel/GetAll/wjNDK08XHXRbtxi9kmkBXg%3d%3d/0","XbrlUrl":"","TedanUrl":"http://www.tedan.ir"}]}